irb_kernel/__init__.py
irb_kernel/__main__.py
irb_kernel/install.py
irb_kernel/kernel.py
irb_kernel-0.2.0.dist-info/LICENSE
irb_kernel-0.2.0.dist-info/WHEEL
irb_kernel-0.2.0.dist-info/METADATA
irb_kernel-0.2.0.dist-info/RECORD
