Metadata-Version: 2.1
Name: irb-kernel
Version: 0.2.0
Summary: A Jupyter kernel for irb (REPL for Ruby programming language)
Author: Kozo Nishida
Author-email: kozo.nishida@gmail.com
Requires-Python: >=3.6,<4.0
Classifier: Programming Language :: Python :: 3
Classifier: Programming Language :: Python :: 3.6
Classifier: Programming Language :: Python :: 3.7
Classifier: Programming Language :: Python :: 3.8
Requires-Dist: notebook (>=6.0.3,<7.0.0)
Requires-Dist: pexpect (>=4.8.0,<5.0.0)
